{"metadata": {"dbt_schema_version": "https://schemas.getdbt.com/dbt/catalog/v1.json", "dbt_version": "1.11.7", "generated_at": "2026-04-13T07:02:52.104032Z", "invocation_id": "874e3564-c71b-4260-8d4f-7bec88e697e1", "invocation_started_at": "2026-04-13T07:02:34.884131Z", "env": {}}, "nodes": {"model.aml_intelligence.stg_transactions": {"metadata": {"type": "VIEW", "schema": "STAGING", "name": "STG_TRANSACTIONS", "database": "AML_DB", "comment": null, "owner": "TRANSFORMER"}, "columns": {"TRANSACTION_ID": {"type": "TEXT", "index": 1, "name": "TRANSACTION_ID", "comment": null}, "CUSTOMER_ID": {"type": "TEXT", "index": 2, "name": "CUSTOMER_ID", "comment": null}, "REFERENCE_NUMBER": {"type": "TEXT", "index": 3, "name": "REFERENCE_NUMBER", "comment": null}, "AMOUNT": {"type": "FLOAT", "index": 4, "name": "AMOUNT", "comment": null}, "CURRENCY": {"type": "TEXT", "index": 5, "name": "CURRENCY", "comment": null}, "AMOUNT_AUD": {"type": "FLOAT", "index": 6, "name": "AMOUNT_AUD", "comment": null}, "IS_LARGE_TRANSACTION": {"type": "BOOLEAN", "index": 7, "name": "IS_LARGE_TRANSACTION", "comment": null}, "IS_NEAR_THRESHOLD": {"type": "BOOLEAN", "index": 8, "name": "IS_NEAR_THRESHOLD", "comment": null}, "TRANSACTION_TYPE": {"type": "TEXT", "index": 9, "name": "TRANSACTION_TYPE", "comment": null}, "CHANNEL": {"type": "TEXT", "index": 10, "name": "CHANNEL", "comment": null}, "MERCHANT_CATEGORY": {"type": "TEXT", "index": 11, "name": "MERCHANT_CATEGORY", "comment": null}, "COUNTERPARTY_COUNTRY": {"type": "TEXT", "index": 12, "name": "COUNTERPARTY_COUNTRY", "comment": null}, "STATUS": {"type": "TEXT", "index": 13, "name": "STATUS", "comment": null}, "TRANSACTION_DATE": {"type": "DATE", "index": 14, "name": "TRANSACTION_DATE", "comment": null}, "TRANSACTION_YEAR": {"type": "NUMBER", "index": 15, "name": "TRANSACTION_YEAR", "comment": null}, "TRANSACTION_MONTH": {"type": "NUMBER", "index": 16, "name": "TRANSACTION_MONTH", "comment": null}, "DAY_OF_WEEK": {"type": "NUMBER", "index": 17, "name": "DAY_OF_WEEK", "comment": null}, "_LOADED_AT": {"type": "TIMESTAMP_LTZ", "index": 18, "name": "_LOADED_AT", "comment": null}}, "stats": {"has_stats": {"id": "has_stats", "label": "Has Stats?", "value": false, "include": false, "description": "Indicates whether there are statistics for this table"}}, "unique_id": "model.aml_intelligence.stg_transactions"}, "seed.aml_intelligence.ref_high_risk_countries": {"metadata": {"type": "BASE TABLE", "schema": "REFERENCE", "name": "REF_HIGH_RISK_COUNTRIES", "database": "AML_DB", "comment": null, "owner": "TRANSFORMER"}, "columns": {"COUNTRY_NAME": {"type": "TEXT", "index": 1, "name": "COUNTRY_NAME", "comment": null}, "RISK_BASIS": {"type": "TEXT", "index": 2, "name": "RISK_BASIS", "comment": null}, "FATF_LISTED": {"type": "TEXT", "index": 3, "name": "FATF_LISTED", "comment": null}, "AUSTRAC_LISTED": {"type": "TEXT", "index": 4, "name": "AUSTRAC_LISTED", "comment": null}, "UPDATED_DATE": {"type": "TEXT", "index": 5, "name": "UPDATED_DATE", "comment": null}}, "stats": {"bytes": {"id": "bytes", "label": "Approximate Size", "value": 1536, "include": true, "description": "Approximate size of the table as reported by Snowflake"}, "last_modified": {"id": "last_modified", "label": "Last Modified", "value": "2026-04-03 06:25UTC", "include": true, "description": "The timestamp for last update/change"}, "row_count": {"id": "row_count", "label": "Row Count", "value": 22, "include": true, "description": "An approximate count of rows in this table"}, "has_stats": {"id": "has_stats", "label": "Has Stats?", "value": true, "include": false, "description": "Indicates whether there are statistics for this table"}}, "unique_id": "seed.aml_intelligence.ref_high_risk_countries"}, "model.aml_intelligence.fct_transactions": {"metadata": {"type": "BASE TABLE", "schema": "MARTS", "name": "FCT_TRANSACTIONS", "database": "AML_DB", "comment": null, "owner": "TRANSFORMER"}, "columns": {"TRANSACTION_KEY": {"type": "TEXT", "index": 1, "name": "TRANSACTION_KEY", "comment": null}, "TRANSACTION_ID": {"type": "TEXT", "index": 2, "name": "TRANSACTION_ID", "comment": null}, "CUSTOMER_KEY": {"type": "TEXT", "index": 3, "name": "CUSTOMER_KEY", "comment": null}, "DATE_ID": {"type": "DATE", "index": 4, "name": "DATE_ID", "comment": null}, "AMOUNT_AUD": {"type": "FLOAT", "index": 5, "name": "AMOUNT_AUD", "comment": null}, "TRANSACTION_TYPE": {"type": "TEXT", "index": 6, "name": "TRANSACTION_TYPE", "comment": null}, "CHANNEL": {"type": "TEXT", "index": 7, "name": "CHANNEL", "comment": null}, "COUNTERPARTY_COUNTRY": {"type": "TEXT", "index": 8, "name": "COUNTERPARTY_COUNTRY", "comment": null}, "TRANSACTION_STATUS": {"type": "TEXT", "index": 9, "name": "TRANSACTION_STATUS", "comment": null}, "FLAG_LARGE_CASH": {"type": "BOOLEAN", "index": 10, "name": "FLAG_LARGE_CASH", "comment": null}, "FLAG_STRUCTURING": {"type": "BOOLEAN", "index": 11, "name": "FLAG_STRUCTURING", "comment": null}, "FLAG_HIGH_RISK_COUNTRY": {"type": "BOOLEAN", "index": 12, "name": "FLAG_HIGH_RISK_COUNTRY", "comment": null}, "FLAG_PEP_CUSTOMER": {"type": "BOOLEAN", "index": 13, "name": "FLAG_PEP_CUSTOMER", "comment": null}, "FLAG_SANCTIONED_CUSTOMER": {"type": "BOOLEAN", "index": 14, "name": "FLAG_SANCTIONED_CUSTOMER", "comment": null}, "RULES_TRIGGERED_COUNT": {"type": "NUMBER", "index": 15, "name": "RULES_TRIGGERED_COUNT", "comment": null}, "IS_FLAGGED": {"type": "BOOLEAN", "index": 16, "name": "IS_FLAGGED", "comment": null}, "CUSTOMER_RISK_RATING": {"type": "TEXT", "index": 17, "name": "CUSTOMER_RISK_RATING", "comment": null}, "CUSTOMER_KYC_STATUS": {"type": "TEXT", "index": 18, "name": "CUSTOMER_KYC_STATUS", "comment": null}, "COMPOSITE_RISK_SCORE": {"type": "NUMBER", "index": 19, "name": "COMPOSITE_RISK_SCORE", "comment": null}, "ENHANCED_DUE_DILIGENCE_TIER": {"type": "TEXT", "index": 20, "name": "ENHANCED_DUE_DILIGENCE_TIER", "comment": null}, "ALERT_ID": {"type": "TEXT", "index": 21, "name": "ALERT_ID", "comment": null}, "ALERT_STATUS": {"type": "TEXT", "index": 22, "name": "ALERT_STATUS", "comment": null}, "ALERT_RISK_SCORE": {"type": "FLOAT", "index": 23, "name": "ALERT_RISK_SCORE", "comment": null}, "ESCALATED_TO_FIU": {"type": "BOOLEAN", "index": 24, "name": "ESCALATED_TO_FIU", "comment": null}, "HAS_ALERT": {"type": "BOOLEAN", "index": 25, "name": "HAS_ALERT", "comment": null}, "FISCAL_YEAR": {"type": "NUMBER", "index": 26, "name": "FISCAL_YEAR", "comment": null}, "FISCAL_MONTH": {"type": "NUMBER", "index": 27, "name": "FISCAL_MONTH", "comment": null}, "QUARTER_LABEL": {"type": "TEXT", "index": 28, "name": "QUARTER_LABEL", "comment": null}, "_UPDATED_AT": {"type": "TIMESTAMP_LTZ", "index": 29, "name": "_UPDATED_AT", "comment": null}}, "stats": {"bytes": {"id": "bytes", "label": "Approximate Size", "value": 369664, "include": true, "description": "Approximate size of the table as reported by Snowflake"}, "clustering_key": {"id": "clustering_key", "label": "Clustering Key", "value": "LINEAR(date_id, customer_key)", "include": true, "description": "The key used to cluster this table"}, "last_modified": {"id": "last_modified", "label": "Last Modified", "value": "2026-04-03 06:26UTC", "include": true, "description": "The timestamp for last update/change"}, "row_count": {"id": "row_count", "label": "Row Count", "value": 5000, "include": true, "description": "An approximate count of rows in this table"}, "has_stats": {"id": "has_stats", "label": "Has Stats?", "value": true, "include": false, "description": "Indicates whether there are statistics for this table"}}, "unique_id": "model.aml_intelligence.fct_transactions"}, "model.aml_intelligence.fct_aml_alerts": {"metadata": {"type": "BASE TABLE", "schema": "MARTS", "name": "FCT_AML_ALERTS", "database": "AML_DB", "comment": null, "owner": "TRANSFORMER"}, "columns": {"ALERT_KEY": {"type": "TEXT", "index": 1, "name": "ALERT_KEY", "comment": null}, "ALERT_ID": {"type": "TEXT", "index": 2, "name": "ALERT_ID", "comment": null}, "TRANSACTION_ID": {"type": "TEXT", "index": 3, "name": "TRANSACTION_ID", "comment": null}, "CUSTOMER_ID": {"type": "TEXT", "index": 4, "name": "CUSTOMER_ID", "comment": null}, "CUSTOMER_KEY": {"type": "TEXT", "index": 5, "name": "CUSTOMER_KEY", "comment": null}, "DATE_ID": {"type": "DATE", "index": 6, "name": "DATE_ID", "comment": null}, "ALERT_TYPE": {"type": "TEXT", "index": 7, "name": "ALERT_TYPE", "comment": null}, "RULE_TRIGGERED": {"type": "TEXT", "index": 8, "name": "RULE_TRIGGERED", "comment": null}, "ALERT_STATUS": {"type": "TEXT", "index": 9, "name": "ALERT_STATUS", "comment": null}, "RISK_SCORE": {"type": "FLOAT", "index": 10, "name": "RISK_SCORE", "comment": null}, "RISK_BAND": {"type": "TEXT", "index": 11, "name": "RISK_BAND", "comment": null}, "ASSIGNED_ANALYST": {"type": "TEXT", "index": 12, "name": "ASSIGNED_ANALYST", "comment": null}, "ESCALATED_TO_FIU": {"type": "BOOLEAN", "index": 13, "name": "ESCALATED_TO_FIU", "comment": null}, "RESOLUTION_NOTES": {"type": "TEXT", "index": 14, "name": "RESOLUTION_NOTES", "comment": null}, "ALERT_DATE": {"type": "DATE", "index": 15, "name": "ALERT_DATE", "comment": null}, "RESOLUTION_DATE": {"type": "DATE", "index": 16, "name": "RESOLUTION_DATE", "comment": null}, "DAYS_TO_RESOLVE": {"type": "NUMBER", "index": 17, "name": "DAYS_TO_RESOLVE", "comment": null}, "IS_BREACHED_SLA": {"type": "BOOLEAN", "index": 18, "name": "IS_BREACHED_SLA", "comment": null}, "ALERT_AGE_DAYS": {"type": "NUMBER", "index": 19, "name": "ALERT_AGE_DAYS", "comment": null}, "TRANSACTION_AMOUNT_AUD": {"type": "FLOAT", "index": 20, "name": "TRANSACTION_AMOUNT_AUD", "comment": null}, "TRANSACTION_TYPE": {"type": "TEXT", "index": 21, "name": "TRANSACTION_TYPE", "comment": null}, "CHANNEL": {"type": "TEXT", "index": 22, "name": "CHANNEL", "comment": null}, "COUNTERPARTY_COUNTRY": {"type": "TEXT", "index": 23, "name": "COUNTERPARTY_COUNTRY", "comment": null}, "TRANSACTION_STATUS": {"type": "TEXT", "index": 24, "name": "TRANSACTION_STATUS", "comment": null}, "FLAG_LARGE_CASH": {"type": "BOOLEAN", "index": 25, "name": "FLAG_LARGE_CASH", "comment": null}, "FLAG_STRUCTURING": {"type": "BOOLEAN", "index": 26, "name": "FLAG_STRUCTURING", "comment": null}, "FLAG_HIGH_RISK_COUNTRY": {"type": "BOOLEAN", "index": 27, "name": "FLAG_HIGH_RISK_COUNTRY", "comment": null}, "RULES_TRIGGERED_COUNT": {"type": "NUMBER", "index": 28, "name": "RULES_TRIGGERED_COUNT", "comment": null}, "CUSTOMER_FULL_NAME": {"type": "TEXT", "index": 29, "name": "CUSTOMER_FULL_NAME", "comment": null}, "CUSTOMER_RISK_RATING": {"type": "TEXT", "index": 30, "name": "CUSTOMER_RISK_RATING", "comment": null}, "CUSTOMER_KYC_STATUS": {"type": "TEXT", "index": 31, "name": "CUSTOMER_KYC_STATUS", "comment": null}, "IS_PEP": {"type": "BOOLEAN", "index": 32, "name": "IS_PEP", "comment": null}, "IS_SANCTIONED": {"type": "BOOLEAN", "index": 33, "name": "IS_SANCTIONED", "comment": null}, "COMPOSITE_RISK_SCORE": {"type": "NUMBER", "index": 34, "name": "COMPOSITE_RISK_SCORE", "comment": null}, "ENHANCED_DUE_DILIGENCE_TIER": {"type": "TEXT", "index": 35, "name": "ENHANCED_DUE_DILIGENCE_TIER", "comment": null}, "CUSTOMER_SEGMENT": {"type": "TEXT", "index": 36, "name": "CUSTOMER_SEGMENT", "comment": null}, "COUNTRY_OF_RESIDENCE": {"type": "TEXT", "index": 37, "name": "COUNTRY_OF_RESIDENCE", "comment": null}, "FISCAL_YEAR": {"type": "NUMBER", "index": 38, "name": "FISCAL_YEAR", "comment": null}, "FISCAL_MONTH": {"type": "NUMBER", "index": 39, "name": "FISCAL_MONTH", "comment": null}, "QUARTER_LABEL": {"type": "TEXT", "index": 40, "name": "QUARTER_LABEL", "comment": null}, "_UPDATED_AT": {"type": "TIMESTAMP_LTZ", "index": 41, "name": "_UPDATED_AT", "comment": null}}, "stats": {"bytes": {"id": "bytes", "label": "Approximate Size", "value": 141312, "include": true, "description": "Approximate size of the table as reported by Snowflake"}, "clustering_key": {"id": "clustering_key", "label": "Clustering Key", "value": "LINEAR(alert_date, alert_status)", "include": true, "description": "The key used to cluster this table"}, "last_modified": {"id": "last_modified", "label": "Last Modified", "value": "2026-04-03 06:26UTC", "include": true, "description": "The timestamp for last update/change"}, "row_count": {"id": "row_count", "label": "Row Count", "value": 1350, "include": true, "description": "An approximate count of rows in this table"}, "has_stats": {"id": "has_stats", "label": "Has Stats?", "value": true, "include": false, "description": "Indicates whether there are statistics for this table"}}, "unique_id": "model.aml_intelligence.fct_aml_alerts"}, "model.aml_intelligence.stg_aml_alerts": {"metadata": {"type": "VIEW", "schema": "STAGING", "name": "STG_AML_ALERTS", "database": "AML_DB", "comment": null, "owner": "TRANSFORMER"}, "columns": {"ALERT_ID": {"type": "TEXT", "index": 1, "name": "ALERT_ID", "comment": null}, "TRANSACTION_ID": {"type": "TEXT", "index": 2, "name": "TRANSACTION_ID", "comment": null}, "CUSTOMER_ID": {"type": "TEXT", "index": 3, "name": "CUSTOMER_ID", "comment": null}, "ALERT_TYPE": {"type": "TEXT", "index": 4, "name": "ALERT_TYPE", "comment": null}, "RULE_TRIGGERED": {"type": "TEXT", "index": 5, "name": "RULE_TRIGGERED", "comment": null}, "ALERT_STATUS": {"type": "TEXT", "index": 6, "name": "ALERT_STATUS", "comment": null}, "RISK_SCORE": {"type": "FLOAT", "index": 7, "name": "RISK_SCORE", "comment": null}, "RISK_BAND": {"type": "TEXT", "index": 8, "name": "RISK_BAND", "comment": null}, "ASSIGNED_ANALYST": {"type": "TEXT", "index": 9, "name": "ASSIGNED_ANALYST", "comment": null}, "ESCALATED_TO_FIU": {"type": "BOOLEAN", "index": 10, "name": "ESCALATED_TO_FIU", "comment": null}, "RESOLUTION_NOTES": {"type": "TEXT", "index": 11, "name": "RESOLUTION_NOTES", "comment": null}, "ALERT_DATE": {"type": "DATE", "index": 12, "name": "ALERT_DATE", "comment": null}, "RESOLUTION_DATE": {"type": "DATE", "index": 13, "name": "RESOLUTION_DATE", "comment": null}, "DAYS_TO_RESOLVE": {"type": "NUMBER", "index": 14, "name": "DAYS_TO_RESOLVE", "comment": null}, "_LOADED_AT": {"type": "TIMESTAMP_LTZ", "index": 15, "name": "_LOADED_AT", "comment": null}}, "stats": {"has_stats": {"id": "has_stats", "label": "Has Stats?", "value": false, "include": false, "description": "Indicates whether there are statistics for this table"}}, "unique_id": "model.aml_intelligence.stg_aml_alerts"}, "model.aml_intelligence.dim_date": {"metadata": {"type": "BASE TABLE", "schema": "MARTS", "name": "DIM_DATE", "database": "AML_DB", "comment": null, "owner": "TRANSFORMER"}, "columns": {"DATE_ID": {"type": "DATE", "index": 1, "name": "DATE_ID", "comment": null}, "FULL_DATE": {"type": "DATE", "index": 2, "name": "FULL_DATE", "comment": null}, "CALENDAR_YEAR": {"type": "NUMBER", "index": 3, "name": "CALENDAR_YEAR", "comment": null}, "CALENDAR_QUARTER": {"type": "NUMBER", "index": 4, "name": "CALENDAR_QUARTER", "comment": null}, "CALENDAR_MONTH": {"type": "NUMBER", "index": 5, "name": "CALENDAR_MONTH", "comment": null}, "MONTH_NAME": {"type": "TEXT", "index": 6, "name": "MONTH_NAME", "comment": null}, "MONTH_NAME_SHORT": {"type": "TEXT", "index": 7, "name": "MONTH_NAME_SHORT", "comment": null}, "CALENDAR_WEEK": {"type": "NUMBER", "index": 8, "name": "CALENDAR_WEEK", "comment": null}, "DAY_OF_MONTH": {"type": "NUMBER", "index": 9, "name": "DAY_OF_MONTH", "comment": null}, "DAY_OF_YEAR": {"type": "NUMBER", "index": 10, "name": "DAY_OF_YEAR", "comment": null}, "DAY_OF_WEEK": {"type": "NUMBER", "index": 11, "name": "DAY_OF_WEEK", "comment": null}, "DAY_NAME": {"type": "TEXT", "index": 12, "name": "DAY_NAME", "comment": null}, "DAY_NAME_SHORT": {"type": "TEXT", "index": 13, "name": "DAY_NAME_SHORT", "comment": null}, "IS_WEEKDAY": {"type": "BOOLEAN", "index": 14, "name": "IS_WEEKDAY", "comment": null}, "IS_WEEKEND": {"type": "BOOLEAN", "index": 15, "name": "IS_WEEKEND", "comment": null}, "IS_MONTH_START": {"type": "BOOLEAN", "index": 16, "name": "IS_MONTH_START", "comment": null}, "IS_MONTH_END": {"type": "BOOLEAN", "index": 17, "name": "IS_MONTH_END", "comment": null}, "FISCAL_YEAR": {"type": "NUMBER", "index": 18, "name": "FISCAL_YEAR", "comment": null}, "FISCAL_MONTH": {"type": "NUMBER", "index": 19, "name": "FISCAL_MONTH", "comment": null}, "IS_TODAY": {"type": "BOOLEAN", "index": 20, "name": "IS_TODAY", "comment": null}, "IS_PAST": {"type": "BOOLEAN", "index": 21, "name": "IS_PAST", "comment": null}, "DATE_STRING": {"type": "TEXT", "index": 22, "name": "DATE_STRING", "comment": null}, "MONTH_YEAR_LABEL": {"type": "TEXT", "index": 23, "name": "MONTH_YEAR_LABEL", "comment": null}, "QUARTER_LABEL": {"type": "TEXT", "index": 24, "name": "QUARTER_LABEL", "comment": null}}, "stats": {"bytes": {"id": "bytes", "label": "Approximate Size", "value": 53248, "include": true, "description": "Approximate size of the table as reported by Snowflake"}, "last_modified": {"id": "last_modified", "label": "Last Modified", "value": "2026-04-03 06:26UTC", "include": true, "description": "The timestamp for last update/change"}, "row_count": {"id": "row_count", "label": "Row Count", "value": 3651, "include": true, "description": "An approximate count of rows in this table"}, "has_stats": {"id": "has_stats", "label": "Has Stats?", "value": true, "include": false, "description": "Indicates whether there are statistics for this table"}}, "unique_id": "model.aml_intelligence.dim_date"}, "seed.aml_intelligence.ref_aml_rules": {"metadata": {"type": "BASE TABLE", "schema": "REFERENCE", "name": "REF_AML_RULES", "database": "AML_DB", "comment": null, "owner": "TRANSFORMER"}, "columns": {"RULE_ID": {"type": "TEXT", "index": 1, "name": "RULE_ID", "comment": null}, "RULE_NAME": {"type": "TEXT", "index": 2, "name": "RULE_NAME", "comment": null}, "ALERT_TYPE": {"type": "TEXT", "index": 3, "name": "ALERT_TYPE", "comment": null}, "DESCRIPTION": {"type": "TEXT", "index": 4, "name": "DESCRIPTION", "comment": null}, "THRESHOLD_VALUE": {"type": "FLOAT", "index": 5, "name": "THRESHOLD_VALUE", "comment": null}, "THRESHOLD_CURRENCY": {"type": "TEXT", "index": 6, "name": "THRESHOLD_CURRENCY", "comment": null}, "REGULATORY_BASIS": {"type": "TEXT", "index": 7, "name": "REGULATORY_BASIS", "comment": null}, "IS_ACTIVE": {"type": "TEXT", "index": 8, "name": "IS_ACTIVE", "comment": null}, "EFFECTIVE_DATE": {"type": "TEXT", "index": 9, "name": "EFFECTIVE_DATE", "comment": null}}, "stats": {"bytes": {"id": "bytes", "label": "Approximate Size", "value": 2560, "include": true, "description": "Approximate size of the table as reported by Snowflake"}, "last_modified": {"id": "last_modified", "label": "Last Modified", "value": "2026-04-03 06:25UTC", "include": true, "description": "The timestamp for last update/change"}, "row_count": {"id": "row_count", "label": "Row Count", "value": 6, "include": true, "description": "An approximate count of rows in this table"}, "has_stats": {"id": "has_stats", "label": "Has Stats?", "value": true, "include": false, "description": "Indicates whether there are statistics for this table"}}, "unique_id": "seed.aml_intelligence.ref_aml_rules"}, "model.aml_intelligence.stg_customers": {"metadata": {"type": "VIEW", "schema": "STAGING", "name": "STG_CUSTOMERS", "database": "AML_DB", "comment": null, "owner": "TRANSFORMER"}, "columns": {"CUSTOMER_ID": {"type": "TEXT", "index": 1, "name": "CUSTOMER_ID", "comment": null}, "FIRST_NAME": {"type": "TEXT", "index": 2, "name": "FIRST_NAME", "comment": null}, "LAST_NAME": {"type": "TEXT", "index": 3, "name": "LAST_NAME", "comment": null}, "FULL_NAME": {"type": "TEXT", "index": 4, "name": "FULL_NAME", "comment": null}, "DATE_OF_BIRTH": {"type": "DATE", "index": 5, "name": "DATE_OF_BIRTH", "comment": null}, "AGE_YEARS": {"type": "NUMBER", "index": 6, "name": "AGE_YEARS", "comment": null}, "COUNTRY_OF_BIRTH": {"type": "TEXT", "index": 7, "name": "COUNTRY_OF_BIRTH", "comment": null}, "COUNTRY_OF_RESIDENCE": {"type": "TEXT", "index": 8, "name": "COUNTRY_OF_RESIDENCE", "comment": null}, "RISK_RATING": {"type": "TEXT", "index": 9, "name": "RISK_RATING", "comment": null}, "KYC_STATUS": {"type": "TEXT", "index": 10, "name": "KYC_STATUS", "comment": null}, "KYC_REVIEW_DATE": {"type": "DATE", "index": 11, "name": "KYC_REVIEW_DATE", "comment": null}, "ONBOARDING_DATE": {"type": "DATE", "index": 12, "name": "ONBOARDING_DATE", "comment": null}, "DAYS_AS_CUSTOMER": {"type": "NUMBER", "index": 13, "name": "DAYS_AS_CUSTOMER", "comment": null}, "IS_PEP": {"type": "BOOLEAN", "index": 14, "name": "IS_PEP", "comment": null}, "IS_SANCTIONED": {"type": "BOOLEAN", "index": 15, "name": "IS_SANCTIONED", "comment": null}, "CUSTOMER_SEGMENT": {"type": "TEXT", "index": 16, "name": "CUSTOMER_SEGMENT", "comment": null}, "ANNUAL_INCOME_BAND": {"type": "TEXT", "index": 17, "name": "ANNUAL_INCOME_BAND", "comment": null}, "RELATIONSHIP_MANAGER": {"type": "TEXT", "index": 18, "name": "RELATIONSHIP_MANAGER", "comment": null}, "_LOADED_AT": {"type": "TIMESTAMP_LTZ", "index": 19, "name": "_LOADED_AT", "comment": null}}, "stats": {"has_stats": {"id": "has_stats", "label": "Has Stats?", "value": false, "include": false, "description": "Indicates whether there are statistics for this table"}}, "unique_id": "model.aml_intelligence.stg_customers"}, "model.aml_intelligence.dim_customer": {"metadata": {"type": "BASE TABLE", "schema": "MARTS", "name": "DIM_CUSTOMER", "database": "AML_DB", "comment": null, "owner": "TRANSFORMER"}, "columns": {"CUSTOMER_KEY": {"type": "TEXT", "index": 1, "name": "CUSTOMER_KEY", "comment": null}, "CUSTOMER_ID": {"type": "TEXT", "index": 2, "name": "CUSTOMER_ID", "comment": null}, "FULL_NAME": {"type": "TEXT", "index": 3, "name": "FULL_NAME", "comment": null}, "CUSTOMER_SEGMENT": {"type": "TEXT", "index": 4, "name": "CUSTOMER_SEGMENT", "comment": null}, "COUNTRY_OF_BIRTH": {"type": "TEXT", "index": 5, "name": "COUNTRY_OF_BIRTH", "comment": null}, "COUNTRY_OF_RESIDENCE": {"type": "TEXT", "index": 6, "name": "COUNTRY_OF_RESIDENCE", "comment": null}, "ONBOARDING_DATE": {"type": "DATE", "index": 7, "name": "ONBOARDING_DATE", "comment": null}, "DAYS_AS_CUSTOMER": {"type": "NUMBER", "index": 8, "name": "DAYS_AS_CUSTOMER", "comment": null}, "ANNUAL_INCOME_BAND": {"type": "TEXT", "index": 9, "name": "ANNUAL_INCOME_BAND", "comment": null}, "RELATIONSHIP_MANAGER": {"type": "TEXT", "index": 10, "name": "RELATIONSHIP_MANAGER", "comment": null}, "DATE_OF_BIRTH": {"type": "DATE", "index": 11, "name": "DATE_OF_BIRTH", "comment": null}, "AGE_YEARS": {"type": "NUMBER", "index": 12, "name": "AGE_YEARS", "comment": null}, "RISK_RATING": {"type": "TEXT", "index": 13, "name": "RISK_RATING", "comment": null}, "KYC_STATUS": {"type": "TEXT", "index": 14, "name": "KYC_STATUS", "comment": null}, "IS_PEP": {"type": "BOOLEAN", "index": 15, "name": "IS_PEP", "comment": null}, "IS_SANCTIONED": {"type": "BOOLEAN", "index": 16, "name": "IS_SANCTIONED", "comment": null}, "COMPOSITE_RISK_SCORE": {"type": "NUMBER", "index": 17, "name": "COMPOSITE_RISK_SCORE", "comment": null}, "ENHANCED_DUE_DILIGENCE_TIER": {"type": "TEXT", "index": 18, "name": "ENHANCED_DUE_DILIGENCE_TIER", "comment": null}, "TOTAL_TRANSACTION_COUNT": {"type": "NUMBER", "index": 19, "name": "TOTAL_TRANSACTION_COUNT", "comment": null}, "TOTAL_TRANSACTION_VOLUME_AUD": {"type": "FLOAT", "index": 20, "name": "TOTAL_TRANSACTION_VOLUME_AUD", "comment": null}, "AVG_TRANSACTION_AMOUNT_AUD": {"type": "FLOAT", "index": 21, "name": "AVG_TRANSACTION_AMOUNT_AUD", "comment": null}, "LARGE_TRANSACTION_COUNT": {"type": "NUMBER", "index": 22, "name": "LARGE_TRANSACTION_COUNT", "comment": null}, "NEAR_THRESHOLD_COUNT": {"type": "NUMBER", "index": 23, "name": "NEAR_THRESHOLD_COUNT", "comment": null}, "DISTINCT_COUNTERPARTY_COUNTRIES": {"type": "NUMBER", "index": 24, "name": "DISTINCT_COUNTERPARTY_COUNTRIES", "comment": null}, "TOTAL_ALERT_COUNT": {"type": "NUMBER", "index": 25, "name": "TOTAL_ALERT_COUNT", "comment": null}, "OPEN_ALERT_COUNT": {"type": "NUMBER", "index": 26, "name": "OPEN_ALERT_COUNT", "comment": null}, "ESCALATED_ALERT_COUNT": {"type": "NUMBER", "index": 27, "name": "ESCALATED_ALERT_COUNT", "comment": null}, "FIU_REFERRAL_COUNT": {"type": "NUMBER", "index": 28, "name": "FIU_REFERRAL_COUNT", "comment": null}, "LAST_TRANSACTION_DATE": {"type": "DATE", "index": 29, "name": "LAST_TRANSACTION_DATE", "comment": null}, "_UPDATED_AT": {"type": "TIMESTAMP_LTZ", "index": 30, "name": "_UPDATED_AT", "comment": null}}, "stats": {"bytes": {"id": "bytes", "label": "Approximate Size", "value": 43520, "include": true, "description": "Approximate size of the table as reported by Snowflake"}, "clustering_key": {"id": "clustering_key", "label": "Clustering Key", "value": "LINEAR(risk_rating)", "include": true, "description": "The key used to cluster this table"}, "last_modified": {"id": "last_modified", "label": "Last Modified", "value": "2026-04-03 06:26UTC", "include": true, "description": "The timestamp for last update/change"}, "row_count": {"id": "row_count", "label": "Row Count", "value": 500, "include": true, "description": "An approximate count of rows in this table"}, "has_stats": {"id": "has_stats", "label": "Has Stats?", "value": true, "include": false, "description": "Indicates whether there are statistics for this table"}}, "unique_id": "model.aml_intelligence.dim_customer"}}, "sources": {"source.aml_intelligence.raw.raw_transactions": {"metadata": {"type": "BASE TABLE", "schema": "RAW", "name": "RAW_TRANSACTIONS", "database": "AML_DB", "comment": null, "owner": "TRANSFORMER"}, "columns": {"TRANSACTION_ID": {"type": "TEXT", "index": 1, "name": "TRANSACTION_ID", "comment": null}, "CUSTOMER_ID": {"type": "TEXT", "index": 2, "name": "CUSTOMER_ID", "comment": null}, "AMOUNT": {"type": "FLOAT", "index": 3, "name": "AMOUNT", "comment": null}, "CURRENCY": {"type": "TEXT", "index": 4, "name": "CURRENCY", "comment": null}, "TRANSACTION_DATE": {"type": "TEXT", "index": 5, "name": "TRANSACTION_DATE", "comment": null}, "TRANSACTION_TYPE": {"type": "TEXT", "index": 6, "name": "TRANSACTION_TYPE", "comment": null}, "COUNTERPARTY_COUNTRY": {"type": "TEXT", "index": 7, "name": "COUNTERPARTY_COUNTRY", "comment": null}, "CHANNEL": {"type": "TEXT", "index": 8, "name": "CHANNEL", "comment": null}, "MERCHANT_CATEGORY": {"type": "TEXT", "index": 9, "name": "MERCHANT_CATEGORY", "comment": null}, "STATUS": {"type": "TEXT", "index": 10, "name": "STATUS", "comment": null}, "REFERENCE_NUMBER": {"type": "TEXT", "index": 11, "name": "REFERENCE_NUMBER", "comment": null}, "_LOADED_AT": {"type": "TIMESTAMP_NTZ", "index": 12, "name": "_LOADED_AT", "comment": null}}, "stats": {"bytes": {"id": "bytes", "label": "Approximate Size", "value": 157184, "include": true, "description": "Approximate size of the table as reported by Snowflake"}, "last_modified": {"id": "last_modified", "label": "Last Modified", "value": "2026-04-03 06:20UTC", "include": true, "description": "The timestamp for last update/change"}, "row_count": {"id": "row_count", "label": "Row Count", "value": 5000, "include": true, "description": "An approximate count of rows in this table"}, "has_stats": {"id": "has_stats", "label": "Has Stats?", "value": true, "include": false, "description": "Indicates whether there are statistics for this table"}}, "unique_id": "source.aml_intelligence.raw.raw_transactions"}, "source.aml_intelligence.raw.raw_aml_alerts": {"metadata": {"type": "BASE TABLE", "schema": "RAW", "name": "RAW_AML_ALERTS", "database": "AML_DB", "comment": null, "owner": "TRANSFORMER"}, "columns": {"ALERT_ID": {"type": "TEXT", "index": 1, "name": "ALERT_ID", "comment": null}, "TRANSACTION_ID": {"type": "TEXT", "index": 2, "name": "TRANSACTION_ID", "comment": null}, "CUSTOMER_ID": {"type": "TEXT", "index": 3, "name": "CUSTOMER_ID", "comment": null}, "ALERT_TYPE": {"type": "TEXT", "index": 4, "name": "ALERT_TYPE", "comment": null}, "RULE_TRIGGERED": {"type": "TEXT", "index": 5, "name": "RULE_TRIGGERED", "comment": null}, "ALERT_DATE": {"type": "TEXT", "index": 6, "name": "ALERT_DATE", "comment": null}, "STATUS": {"type": "TEXT", "index": 7, "name": "STATUS", "comment": null}, "ASSIGNED_ANALYST": {"type": "TEXT", "index": 8, "name": "ASSIGNED_ANALYST", "comment": null}, "RISK_SCORE": {"type": "FLOAT", "index": 9, "name": "RISK_SCORE", "comment": null}, "RESOLUTION_DATE": {"type": "TEXT", "index": 10, "name": "RESOLUTION_DATE", "comment": null}, "RESOLUTION_NOTES": {"type": "TEXT", "index": 11, "name": "RESOLUTION_NOTES", "comment": null}, "ESCALATED_TO_FIU": {"type": "TEXT", "index": 12, "name": "ESCALATED_TO_FIU", "comment": null}, "_LOADED_AT": {"type": "TIMESTAMP_NTZ", "index": 13, "name": "_LOADED_AT", "comment": null}}, "stats": {"bytes": {"id": "bytes", "label": "Approximate Size", "value": 44032, "include": true, "description": "Approximate size of the table as reported by Snowflake"}, "last_modified": {"id": "last_modified", "label": "Last Modified", "value": "2026-04-03 06:20UTC", "include": true, "description": "The timestamp for last update/change"}, "row_count": {"id": "row_count", "label": "Row Count", "value": 1350, "include": true, "description": "An approximate count of rows in this table"}, "has_stats": {"id": "has_stats", "label": "Has Stats?", "value": true, "include": false, "description": "Indicates whether there are statistics for this table"}}, "unique_id": "source.aml_intelligence.raw.raw_aml_alerts"}, "source.aml_intelligence.raw.raw_customers": {"metadata": {"type": "BASE TABLE", "schema": "RAW", "name": "RAW_CUSTOMERS", "database": "AML_DB", "comment": null, "owner": "TRANSFORMER"}, "columns": {"CUSTOMER_ID": {"type": "TEXT", "index": 1, "name": "CUSTOMER_ID", "comment": null}, "FIRST_NAME": {"type": "TEXT", "index": 2, "name": "FIRST_NAME", "comment": null}, "LAST_NAME": {"type": "TEXT", "index": 3, "name": "LAST_NAME", "comment": null}, "DATE_OF_BIRTH": {"type": "TEXT", "index": 4, "name": "DATE_OF_BIRTH", "comment": null}, "COUNTRY_OF_BIRTH": {"type": "TEXT", "index": 5, "name": "COUNTRY_OF_BIRTH", "comment": null}, "COUNTRY_OF_RESIDENCE": {"type": "TEXT", "index": 6, "name": "COUNTRY_OF_RESIDENCE", "comment": null}, "RISK_RATING": {"type": "TEXT", "index": 7, "name": "RISK_RATING", "comment": null}, "KYC_STATUS": {"type": "TEXT", "index": 8, "name": "KYC_STATUS", "comment": null}, "KYC_REVIEW_DATE": {"type": "TEXT", "index": 9, "name": "KYC_REVIEW_DATE", "comment": null}, "ONBOARDING_DATE": {"type": "TEXT", "index": 10, "name": "ONBOARDING_DATE", "comment": null}, "CUSTOMER_SEGMENT": {"type": "TEXT", "index": 11, "name": "CUSTOMER_SEGMENT", "comment": null}, "ANNUAL_INCOME_BAND": {"type": "TEXT", "index": 12, "name": "ANNUAL_INCOME_BAND", "comment": null}, "RELATIONSHIP_MANAGER": {"type": "TEXT", "index": 13, "name": "RELATIONSHIP_MANAGER", "comment": null}, "IS_PEP": {"type": "TEXT", "index": 14, "name": "IS_PEP", "comment": null}, "IS_SANCTIONED": {"type": "TEXT", "index": 15, "name": "IS_SANCTIONED", "comment": null}, "_LOADED_AT": {"type": "TIMESTAMP_NTZ", "index": 16, "name": "_LOADED_AT", "comment": null}}, "stats": {"bytes": {"id": "bytes", "label": "Approximate Size", "value": 19456, "include": true, "description": "Approximate size of the table as reported by Snowflake"}, "last_modified": {"id": "last_modified", "label": "Last Modified", "value": "2026-04-03 06:20UTC", "include": true, "description": "The timestamp for last update/change"}, "row_count": {"id": "row_count", "label": "Row Count", "value": 500, "include": true, "description": "An approximate count of rows in this table"}, "has_stats": {"id": "has_stats", "label": "Has Stats?", "value": true, "include": false, "description": "Indicates whether there are statistics for this table"}}, "unique_id": "source.aml_intelligence.raw.raw_customers"}}, "errors": null}